handy_dict/__init__.py
handy_dict/_nbdev.py
handy_dict/apply_keyed.py
handy_dict/core.py
handy_dict/exceptions.py
handy_dict/multi_get.py
handy_dict/return_keyed.py
handy_dict-0.1.0.dist-info/LICENSE
handy_dict-0.1.0.dist-info/METADATA
handy_dict-0.1.0.dist-info/WHEEL
handy_dict-0.1.0.dist-info/entry_points.txt
handy_dict-0.1.0.dist-info/top_level.txt
handy_dict-0.1.0.dist-info/RECORD
