Metadata-Version: 2.1
Name: handy-dict
Version: 0.1.0
Summary: A handy library to manipulate dictionaries
Home-page: https://github.com/fferegrino/handy_dict
Author: Antonio Feregrino
Author-email: antonio.feregrino@gmail.com
License: Apache Software License 2.0
Keywords: dictionaries dictionary
Platform: UNKNOWN
Classifier: Development Status :: 3 - Alpha
Classifier: Intended Audience :: Developers
Classifier: License :: OSI Approved :: Apache Software License
Classifier: Natural Language :: English
Classifier: Programming Language :: Python :: 3.6
Classifier: Programming Language :: Python :: 3.7
Classifier: Programming Language :: Python :: 3.8
Requires-Python: >=3.6
